src/__init__.py
src/module.py
uhyuhjfewfyuwgfyukgyukefwgyukefwgyiewfgyilewfgyliefgyuliwefgyulei-0.1.dist-info/METADATA
uhyuhjfewfyuwgfyukgyukefwgyukefwgyiewfgyilewfgyliefgyuliwefgyulei-0.1.dist-info/WHEEL
uhyuhjfewfyuwgfyukgyukefwgyukefwgyiewfgyilewfgyliefgyuliwefgyulei-0.1.dist-info/top_level.txt
uhyuhjfewfyuwgfyukgyukefwgyukefwgyiewfgyilewfgyliefgyuliwefgyulei-0.1.dist-info/RECORD
