Metadata-Version: 2.4
Name: uhyuhjfewfyuwgfyukgyukefwgyukefwgyiewfgyilewfgyliefgyuliwefgyulei
Version: 0.1
Summary: А ПЛЮС БЭ
Home-page: https://github.com/твой-профиль/my_package
Author: KONSTANTIN
Author-email: konstantin@RUSpochta.kz
Classifier: Programming Language :: Python :: 3
Dynamic: author
Dynamic: author-email
Dynamic: classifier
Dynamic: description
Dynamic: description-content-type
Dynamic: home-page
Dynamic: summary
